api/__init__.py
api/client.py
api/context.py
api/exceptions.py
api/querier.py
api/transport.py
models/AccountAuthOperations.py
models/__init__.py
models/accounts.py
models/address.py
models/auth.py
models/base_transactions.py
models/credits.py
models/data_entries.py
models/enums.py
models/errors.py
models/events.py
models/faucet.py
models/fee_schedule.py
models/general.py
models/key_management.py
models/key_signature.py
models/node_info.py
models/options.py
models/protocol.py
models/queries.py
models/records.py
models/responses.py
models/search.py
models/service.py
models/signature_types.py
models/signatures.py
models/submission.py
models/transaction_results.py
models/transactions.py
models/txid.py
models/txid_set.py
models/types.py
signing/__init__.py
signing/builder.py
signing/signature_handler.py
signing/signer.py
signing/timestamp.py
utils/__init__.py
utils/address_from.py
utils/address_parse.py
utils/config.py
utils/conversion.py
utils/eip712.py
utils/encoding.py
utils/fields.py
utils/formatting.py
utils/hash_functions.py
utils/import_helpers.py
utils/protocols.py
utils/rational.py
utils/union.py
utils/url.py
utils/validation.py
accumulate_python_client-0.1.1.dist-info/LICENSE
accumulate_python_client-0.1.1.dist-info/METADATA
accumulate_python_client-0.1.1.dist-info/WHEEL
accumulate_python_client-0.1.1.dist-info/entry_points.txt
accumulate_python_client-0.1.1.dist-info/top_level.txt
accumulate_python_client-0.1.1.dist-info/RECORD
