Metadata-Version: 2.2
Name: accumulate-python-client
Version: 0.1.1
Summary: A Python client for interacting with the Accumulate Protocol.
Home-page: https://github.com/opendlt/accumulate-python-client
Author: JKG
Author-email: Jason Gregoire <jason.gregoire@example.com>
License: MIT
Keywords: blockchain,accumulate,cryptocurrency
Classifier: Programming Language :: Python :: 3
Classifier: License :: OSI Approved :: MIT License
Classifier: Operating System :: OS Independent
Requires-Python: >=3.8
License-File: LICENSE
Requires-Dist: requests>=2.31.0
Requires-Dist: websockets>=10.4
Requires-Dist: ecdsa>=0.18.0
Requires-Dist: eth-keys>=0.4.0
Requires-Dist: pycryptodome>=3.17.0
Requires-Dist: typing-extensions>=4.7.1
Requires-Dist: protobuf>=4.24.3
Provides-Extra: dev
Requires-Dist: pytest; extra == "dev"
Requires-Dist: pytest-asyncio; extra == "dev"
Requires-Dist: pytest-mock; extra == "dev"
Requires-Dist: pytest-cov; extra == "dev"
Dynamic: author
Dynamic: home-page
Dynamic: provides-extra
Dynamic: requires-python
